catalogue/__init__.py
catalogue/create_db.py
catalogue/download_sky.py
catalogue/download_stars.py
catalogue/drop_db.py
catalogue/models.py
catalogue/prepare_db.py
catalogue/view_downloads.py
catalogue/view_sky.py
gilmenel/__init__.py
gilmenel/astroquery.py
gilmenel/diagrams.py
gilmenel/exceptions.py
gilmenel/gilmenel.py
gilmenel/instruments.py
gilmenel/mocks.py
gilmenel/observatories.py
gilmenel/sources.py
gilmenel/telescopes.py
version/__init__.py
version/_version.py
gilmenel-0.8.1.dist-info/LICENSE
gilmenel-0.8.1.dist-info/METADATA
gilmenel-0.8.1.dist-info/WHEEL
gilmenel-0.8.1.dist-info/top_level.txt
gilmenel-0.8.1.dist-info/RECORD
