Metadata-Version: 2.1
Name: gilmenel
Version: 0.8.1
Summary: Telescope guide star selection tools.
Home-page: https://bitbucket.org/saao/gilmenel
Author: SALT Software Engineers
Author-email: salt-support@salt.ac.za
License: MIT license
Platform: UNKNOWN
Classifier: License :: OSI Approved :: MIT License
Classifier: Operating System :: OS Independent
Classifier: Intended Audience :: Developers
Classifier: Natural Language :: English
Classifier: Programming Language :: Python :: 3
Requires-Python: >=3.6
Requires-Dist: astropy
Requires-Dist: astroquery
Requires-Dist: sqlalchemy
Requires-Dist: matplotlib
Requires-Dist: click
Requires-Dist: tqdm
